mm_poe/__init__.py
mm_poe/__main__.py
mm_poe/cli.py
mm_poe/methods/__init__.py
mm_poe/methods/language_modeling.py
mm_poe/methods/process_of_elimination.py
mm_poe/methods/process_of_elimination_vqa.py
mm_poe/methods/vision_language_modeling.py
mm_poe/methods/utils/__init__.py
mm_poe/methods/utils/data.py
mm_poe/methods/utils/methods.py
mm_poe/methods/utils/models.py
mm_poe/methods/utils/utils.py
mm_poe/models/__init__.py
mm_poe/models/model_downloaders/__init__.py
mm_poe/models/model_downloaders/model_downloaders.py
mm_poe-1.0.4.dist-info/LICENSE
mm_poe-1.0.4.dist-info/METADATA
mm_poe-1.0.4.dist-info/WHEEL
mm_poe-1.0.4.dist-info/entry_points.txt
mm_poe-1.0.4.dist-info/top_level.txt
mm_poe-1.0.4.dist-info/RECORD
