Metadata-Version: 2.2
Name: mm_poe
Version: 1.0.4
Summary: Multiple Choice Reasoning via. Process of Elimination using Multi-Modal Models
Home-page: https://github.com/souradipp76/MM-PoE/
Author: souradipp76
License-File: LICENSE
Requires-Dist: transformers
Requires-Dist: datasets
Requires-Dist: torch
Requires-Dist: huggingface_hub
Requires-Dist: bitsandbytes
Requires-Dist: accelerate
Requires-Dist: questionary
Requires-Dist: pillow
Requires-Dist: gdown
Provides-Extra: test
Requires-Dist: pytest; extra == "test"
Requires-Dist: coverage; extra == "test"
Requires-Dist: flake8; extra == "test"
Requires-Dist: black; extra == "test"
Requires-Dist: isort; extra == "test"
Requires-Dist: pytest-cov; extra == "test"
Requires-Dist: mypy; extra == "test"
Requires-Dist: gitchangelog; extra == "test"
Requires-Dist: mkdocs; extra == "test"
Dynamic: author
Dynamic: description
Dynamic: description-content-type
Dynamic: home-page
Dynamic: provides-extra
Dynamic: requires-dist
Dynamic: summary
